examples/1_solving.py
examples/2_par_estimation.py
examples/3_par_estimation_glos.py
examples/4_par_scanning.py
examples/5_dxdt.py
examples/6_dyn_sens.py
examples/7_glyoxalase_discrim_2m.py
examples/TSH2a.txt
examples/TSH2b.txt
examples/glos_2m_extKL_final_pop.txt
examples/plotgenerations.py
examples/profile_par_scanning.py
stimator/GDE3solver.py
stimator/__init__.py
stimator/de.py
stimator/dynamics.py
stimator/estimation.py
stimator/fim.py
stimator/kinetics.py
stimator/model.py
stimator/modelparser.py
stimator/plots.py
stimator/timecourse.py
stimator/utils.py
stimator/versions.py
stimator/examples/__init__.py
stimator/examples/models.py
stimator/examples/timecourses/TSH2a.txt
stimator/examples/timecourses/TSH2b.txt
stimator/examples/timecourses/tc_double.txt
stimator/moo/__init__.py
stimator/moo/rmc.py
stimator/moo/sorting.py
tests/__init__.py
tests/run.py
tests/test_model.py
tests/test_modelparser.py
tests/test_timecourse.py
stimator-0.9.135.dist-info/LICENSE
stimator-0.9.135.dist-info/METADATA
stimator-0.9.135.dist-info/WHEEL
stimator-0.9.135.dist-info/top_level.txt
stimator-0.9.135.dist-info/RECORD
